koordinates/__init__.py
koordinates/base.py
koordinates/catalog.py
koordinates/client.py
koordinates/exceptions.py
koordinates/exports.py
koordinates/layers.py
koordinates/licenses.py
koordinates/metadata.py
koordinates/permissions.py
koordinates/publishing.py
koordinates/sets.py
koordinates/sources.py
koordinates/users.py
koordinates/utils.py
koordinates-0.7.1.dist-info/LICENSE
koordinates-0.7.1.dist-info/METADATA
koordinates-0.7.1.dist-info/WHEEL
koordinates-0.7.1.dist-info/top_level.txt
koordinates-0.7.1.dist-info/RECORD
