Metadata-Version: 2.1
Name: koordinates
Version: 0.7.1
Summary: A Python client library for a number of Koordinates web APIs
Author-email: Koordinates Limited <support@koordinates.com>
Project-URL: Source, https://github.com/koordinates/python-client
Keywords: koordinates,api
Classifier: Development Status :: 5 - Production/Stable
Classifier: Intended Audience :: Developers
Classifier: License :: OSI Approved :: BSD License
Classifier: Operating System :: OS Independent
Classifier: Programming Language :: Python :: 3.7
Classifier: Programming Language :: Python :: 3.8
Classifier: Programming Language :: Python :: 3.9
Classifier: Programming Language :: Python :: 3.10
Classifier: Topic :: Software Development :: Libraries :: Python Modules
Classifier: Topic :: Scientific/Engineering :: GIS
Requires-Python: >=3.7
License-File: LICENSE
Requires-Dist: python-dateutil <3,>=2
Requires-Dist: pytz
Requires-Dist: requests <3,>=2.5
Requires-Dist: requests-toolbelt
Requires-Dist: importlib-metadata ; python_version < "3.8"
Provides-Extra: dev
Requires-Dist: coverage <4,>=3.7 ; extra == 'dev'
Requires-Dist: pytest >=3.3 ; extra == 'dev'
Requires-Dist: responses >=0.3 ; extra == 'dev'
